codereviewpkg/__init__.py
codereviewpkg/cli.py
codereviewpkg/core.py
codereviewpkg-0.1.1.dist-info/licenses/LICENSE
codereviewpkg-0.1.1.dist-info/METADATA
codereviewpkg-0.1.1.dist-info/WHEEL
codereviewpkg-0.1.1.dist-info/entry_points.txt
codereviewpkg-0.1.1.dist-info/top_level.txt
codereviewpkg-0.1.1.dist-info/RECORD
